__init__.py
abcdict.py
abcutil.py
abcDict-0.0.6.dist-info/LICENSE
abcDict-0.0.6.dist-info/METADATA
abcDict-0.0.6.dist-info/WHEEL
abcDict-0.0.6.dist-info/top_level.txt
abcDict-0.0.6.dist-info/RECORD
