Metadata-Version: 2.1
Name: abcDict
Version: 0.0.6
Summary: use yaml config easy
Author-email: msbrm <cuihaniss@gmail.com>
Project-URL: Homepage, https://github.com/msbrm/abcDict/tree/main
Project-URL: Bug Tracker, https://github.com/msbrm/abcDict/issues
Classifier: Programming Language :: Python :: 3
Classifier: License :: OSI Approved :: MIT License
Requires-Python: >=3.8
License-File: LICENSE
